niaarmts/NiaARMTS.py
niaarmts/__init__.py
niaarmts/dataset.py
niaarmts/explainability.py
niaarmts/feature.py
niaarmts/metrics.py
niaarmts/rule.py
niaarmts/rule_stability.py
niaarmts/visualization.py
niaarmts-0.2.6.dist-info/LICENSE
niaarmts-0.2.6.dist-info/METADATA
niaarmts-0.2.6.dist-info/WHEEL
niaarmts-0.2.6.dist-info/RECORD
