Metadata-Version: 2.1
Name: niaarmts
Version: 0.2.6
Summary: Time series numerical association rule mining variants
Home-page: https://github.com/firefly-cpp/NiaARMTS
Author: Iztok Fister Jr.
Author-email: iztok@iztok-jr-fister.eu
Requires-Python: >=3.11,<3.14
Classifier: Programming Language :: Python :: 3
Classifier: Programming Language :: Python :: 3.11
Classifier: Programming Language :: Python :: 3.12
Classifier: Programming Language :: Python :: 3.13
Provides-Extra: docs
Requires-Dist: matplotlib (>=3.10.1,<4.0.0)
Requires-Dist: niapy (>=2.5.2,<3.0.0)
Requires-Dist: numpy (>=1.26.1,<2.0.0)
Requires-Dist: pandas (>=2.2.3,<3.0.0)
Requires-Dist: sphinx-rtd-theme[docs] (>=1.0.0,<2.0.0) ; extra == "docs"
Requires-Dist: sphinx[docs] (>=5.0,<6.0) ; extra == "docs"
Project-URL: Repository, https://github.com/firefly-cpp/NiaARMTS
